{
    "url": "https://api.github.com/repos/thundernest/k-9/issues/5492",
    "repository_url": "https://api.github.com/repos/thundernest/k-9",
    "labels_url": "https://api.github.com/repos/thundernest/k-9/issues/5492/labels{/name}",
    "comments_url": "https://api.github.com/repos/thundernest/k-9/issues/5492/comments",
    "events_url": "https://api.github.com/repos/thundernest/k-9/issues/5492/events",
    "html_url": "https://github.com/thundernest/k-9/pull/5492",
    "id": 957278851,
    "node_id": "MDExOlB1bGxSZXF1ZXN0NzAwNzM1ODE4",
    "number": 5492,
    "title": "Support archive/spam action in message lists with multiple accounts",
    "user": {
        "login": "cketti",
        "id": 218061,
        "node_id": "MDQ6VXNlcjIxODA2MQ==",
        "avatar_url": "https://avatars.githubusercontent.com/u/218061?v=4",
        "gravatar_id": "",
        "url": "https://api.github.com/users/cketti",
        "html_url": "https://github.com/cketti",
        "followers_url": "https://api.github.com/users/cketti/followers",
        "following_url": "https://api.github.com/users/cketti/following{/other_user}",
        "gists_url": "https://api.github.com/users/cketti/gists{/gist_id}",
        "starred_url": "https://api.github.com/users/cketti/starred{/owner}{/repo}",
        "subscriptions_url": "https://api.github.com/users/cketti/subscriptions",
        "organizations_url": "https://api.github.com/users/cketti/orgs",
        "repos_url": "https://api.github.com/users/cketti/repos",
        "events_url": "https://api.github.com/users/cketti/events{/privacy}",
        "received_events_url": "https://api.github.com/users/cketti/received_events",
        "type": "User",
        "site_admin": false
    },
    "labels": [],
    "state": "closed",
    "locked": false,
    "assignee": null,
    "assignees": [],
    "milestone": null,
    "comments": 0,
    "created_at": "2021-07-31T16:40:26Z",
    "updated_at": "2021-08-02T11:57:20Z",
    "closed_at": "2021-08-02T11:57:19Z",
    "author_association": "MEMBER",
    "active_lock_reason": null,
    "draft": false,
    "pull_request": {
        "url": "https://api.github.com/repos/thundernest/k-9/pulls/5492",
        "html_url": "https://github.com/thundernest/k-9/pull/5492",
        "diff_url": "https://github.com/thundernest/k-9/pull/5492.diff",
        "patch_url": "https://github.com/thundernest/k-9/pull/5492.patch",
        "merged_at": "2021-08-02T11:57:19Z"
    },
    "body": "When the account of at least one selected message has a designated archive/spam folder we now display the archive/spam actions. The messages that can't be moved because their account doesn't have an archive/spam folder will simply remain where they are.\r\n\r\nhttps://user-images.githubusercontent.com/218061/127746461-d59e4002-c7b4-4e92-b98f-3b351bac3c8b.mp4\r\n\r\nCloses #667\r\nCloses #1041\r\nCloses #5069\r\n",
    "closed_by": {
        "login": "cketti",
        "id": 218061,
        "node_id": "MDQ6VXNlcjIxODA2MQ==",
        "avatar_url": "https://avatars.githubusercontent.com/u/218061?v=4",
        "gravatar_id": "",
        "url": "https://api.github.com/users/cketti",
        "html_url": "https://github.com/cketti",
        "followers_url": "https://api.github.com/users/cketti/followers",
        "following_url": "https://api.github.com/users/cketti/following{/other_user}",
        "gists_url": "https://api.github.com/users/cketti/gists{/gist_id}",
        "starred_url": "https://api.github.com/users/cketti/starred{/owner}{/repo}",
        "subscriptions_url": "https://api.github.com/users/cketti/subscriptions",
        "organizations_url": "https://api.github.com/users/cketti/orgs",
        "repos_url": "https://api.github.com/users/cketti/repos",
        "events_url": "https://api.github.com/users/cketti/events{/privacy}",
        "received_events_url": "https://api.github.com/users/cketti/received_events",
        "type": "User",
        "site_admin": false
    },
    "reactions": {
        "url": "https://api.github.com/repos/thundernest/k-9/issues/5492/reactions",
        "total_count": 0,
        "+1": 0,
        "-1": 0,
        "laugh": 0,
        "hooray": 0,
        "confused": 0,
        "heart": 0,
        "rocket": 0,
        "eyes": 0
    },
    "timeline_url": "https://api.github.com/repos/thundernest/k-9/issues/5492/timeline",
    "performed_via_github_app": null,
    "state_reason": null
}