{
    "url": "https://api.github.com/repos/kiwix/kiwix-android/issues/3252",
    "repository_url": "https://api.github.com/repos/kiwix/kiwix-android",
    "labels_url": "https://api.github.com/repos/kiwix/kiwix-android/issues/3252/labels{/name}",
    "comments_url": "https://api.github.com/repos/kiwix/kiwix-android/issues/3252/comments",
    "events_url": "https://api.github.com/repos/kiwix/kiwix-android/issues/3252/events",
    "html_url": "https://github.com/kiwix/kiwix-android/pull/3252",
    "id": 1600098415,
    "node_id": "PR_kwDOBLs03M5Kxn5G",
    "number": 3252,
    "title": "fixed storage denied toast loop issue",
    "user": {
        "login": "criticalAY",
        "id": 48384865,
        "node_id": "MDQ6VXNlcjQ4Mzg0ODY1",
        "avatar_url": "https://avatars.githubusercontent.com/u/48384865?v=4",
        "gravatar_id": "",
        "url": "https://api.github.com/users/criticalAY",
        "html_url": "https://github.com/criticalAY",
        "followers_url": "https://api.github.com/users/criticalAY/followers",
        "following_url": "https://api.github.com/users/criticalAY/following{/other_user}",
        "gists_url": "https://api.github.com/users/criticalAY/gists{/gist_id}",
        "starred_url": "https://api.github.com/users/criticalAY/starred{/owner}{/repo}",
        "subscriptions_url": "https://api.github.com/users/criticalAY/subscriptions",
        "organizations_url": "https://api.github.com/users/criticalAY/orgs",
        "repos_url": "https://api.github.com/users/criticalAY/repos",
        "events_url": "https://api.github.com/users/criticalAY/events{/privacy}",
        "received_events_url": "https://api.github.com/users/criticalAY/received_events",
        "type": "User",
        "site_admin": false
    },
    "labels": [],
    "state": "closed",
    "locked": false,
    "assignee": null,
    "assignees": [],
    "milestone": null,
    "comments": 3,
    "created_at": "2023-02-26T15:32:28Z",
    "updated_at": "2023-02-26T20:09:26Z",
    "closed_at": "2023-02-26T20:09:26Z",
    "author_association": "CONTRIBUTOR",
    "active_lock_reason": null,
    "draft": false,
    "pull_request": {
        "url": "https://api.github.com/repos/kiwix/kiwix-android/pulls/3252",
        "html_url": "https://github.com/kiwix/kiwix-android/pull/3252",
        "diff_url": "https://github.com/kiwix/kiwix-android/pull/3252.diff",
        "patch_url": "https://github.com/kiwix/kiwix-android/pull/3252.patch",
        "merged_at": null
    },
    "body": "<!--\r\n- Add the issue number here.\r\n\r\n- If you haven't solved the issue completely use \"Linked issue #{issue_number}.\r\n- After solving the issue completely change it to \"Fixes #{issue_number}.\r\n-->\r\nFixes #3251\r\n\r\n<!-- Add here what changes were made in this issue and if possible provide links. -->\r\n\r\n\r\n<!-- If possible, please add relevant screenshots / GIFs -->\r\n\r\n**Screenshots** \r\n\r\nhttps://user-images.githubusercontent.com/48384865/221428756-38a5bb63-0be4-4c0d-bc64-1274d1a6d91b.mp4\r\n\r\n\r\n",
    "closed_by": {
        "login": "kelson42",
        "id": 1029718,
        "node_id": "MDQ6VXNlcjEwMjk3MTg=",
        "avatar_url": "https://avatars.githubusercontent.com/u/1029718?v=4",
        "gravatar_id": "",
        "url": "https://api.github.com/users/kelson42",
        "html_url": "https://github.com/kelson42",
        "followers_url": "https://api.github.com/users/kelson42/followers",
        "following_url": "https://api.github.com/users/kelson42/following{/other_user}",
        "gists_url": "https://api.github.com/users/kelson42/gists{/gist_id}",
        "starred_url": "https://api.github.com/users/kelson42/starred{/owner}{/repo}",
        "subscriptions_url": "https://api.github.com/users/kelson42/subscriptions",
        "organizations_url": "https://api.github.com/users/kelson42/orgs",
        "repos_url": "https://api.github.com/users/kelson42/repos",
        "events_url": "https://api.github.com/users/kelson42/events{/privacy}",
        "received_events_url": "https://api.github.com/users/kelson42/received_events",
        "type": "User",
        "site_admin": false
    },
    "reactions": {
        "url": "https://api.github.com/repos/kiwix/kiwix-android/issues/3252/reactions",
        "total_count": 0,
        "+1": 0,
        "-1": 0,
        "laugh": 0,
        "hooray": 0,
        "confused": 0,
        "heart": 0,
        "rocket": 0,
        "eyes": 0
    },
    "timeline_url": "https://api.github.com/repos/kiwix/kiwix-android/issues/3252/timeline",
    "performed_via_github_app": null,
    "state_reason": null
}