{
    "url": "https://api.github.com/repos/mozilla-mobile/focus-android/issues/7536",
    "repository_url": "https://api.github.com/repos/mozilla-mobile/focus-android",
    "labels_url": "https://api.github.com/repos/mozilla-mobile/focus-android/issues/7536/labels{/name}",
    "comments_url": "https://api.github.com/repos/mozilla-mobile/focus-android/issues/7536/comments",
    "events_url": "https://api.github.com/repos/mozilla-mobile/focus-android/issues/7536/events",
    "html_url": "https://github.com/mozilla-mobile/focus-android/issues/7536",
    "id": 1348037711,
    "node_id": "I_kwDOBIeEJM5QWWxP",
    "number": 7536,
    "title": "Private session is closed after denying permissions ",
    "user": {
        "login": "delia-pop",
        "id": 89388888,
        "node_id": "MDQ6VXNlcjg5Mzg4ODg4",
        "avatar_url": "https://avatars.githubusercontent.com/u/89388888?v=4",
        "gravatar_id": "",
        "url": "https://api.github.com/users/delia-pop",
        "html_url": "https://github.com/delia-pop",
        "followers_url": "https://api.github.com/users/delia-pop/followers",
        "following_url": "https://api.github.com/users/delia-pop/following{/other_user}",
        "gists_url": "https://api.github.com/users/delia-pop/gists{/gist_id}",
        "starred_url": "https://api.github.com/users/delia-pop/starred{/owner}{/repo}",
        "subscriptions_url": "https://api.github.com/users/delia-pop/subscriptions",
        "organizations_url": "https://api.github.com/users/delia-pop/orgs",
        "repos_url": "https://api.github.com/users/delia-pop/repos",
        "events_url": "https://api.github.com/users/delia-pop/events{/privacy}",
        "received_events_url": "https://api.github.com/users/delia-pop/received_events",
        "type": "User",
        "site_admin": false
    },
    "labels": [
        {
            "id": 497359850,
            "node_id": "MDU6TGFiZWw0OTczNTk4NTA=",
            "url": "https://api.github.com/repos/mozilla-mobile/focus-android/labels/bug",
            "name": "bug",
            "color": "ee0701",
            "default": true,
            "description": null
        },
        {
            "id": 4295308208,
            "node_id": "LA_kwDOBIeEJM8AAAABAAUzsA",
            "url": "https://api.github.com/repos/mozilla-mobile/focus-android/labels/Feature:SitePermissions",
            "name": "Feature:SitePermissions",
            "color": "4FA1FE",
            "default": false,
            "description": ""
        },
        {
            "id": 4365226207,
            "node_id": "LA_kwDOBIeEJM8AAAABBDAQ3w",
            "url": "https://api.github.com/repos/mozilla-mobile/focus-android/labels/S2",
            "name": "S2",
            "color": "93f9d4",
            "default": false,
            "description": "Major Functionality/product severely impaired and a satisfactory workaround doesn't exist"
        }
    ],
    "state": "closed",
    "locked": true,
    "assignee": null,
    "assignees": [],
    "milestone": null,
    "comments": 1,
    "created_at": "2022-08-23T14:19:02Z",
    "updated_at": "2022-11-26T05:34:26Z",
    "closed_at": "2022-11-26T05:34:26Z",
    "author_association": "NONE",
    "active_lock_reason": null,
    "body": "## Steps to reproduce\r\n1. Go to https://mozilla.github.io/webrtc-landing/gum_test.html. \r\n2. Select \"Camera\".\r\n3. Tap \"Allow\".\r\n4. Send the app in background.\r\n5. Go to the device's settings, to Apps - Focus - Permissions, and turn the Camera custom setting toggle off.\r\n6. Access Focus and observe if the page is step 1 is still open.\r\n\r\n### Expected behavior\r\nThe browsing session should remain opened.\r\n### Actual behavior\r\nThe browsing session is automatically ended after denying the permission.\r\n### Device information\r\n\r\n* Android device: Google Pixel 6 (Android 13)\r\n* Focus version: Latest Nightly 106.0a1, Beta 105.0b1, also reproducible on Fenix in Private Mode.\r\nNote that on Fenix Normal Browsing, the session is not closed, only restarted.\r\n\r\nhttps://user-images.githubusercontent.com/89388888/186182226-96c408d0-3eec-4f32-8f89-4e631aed2c46.mp4\r\n\r\n\r\n",
    "closed_by": {
        "login": "cpeterso",
        "id": 629193,
        "node_id": "MDQ6VXNlcjYyOTE5Mw==",
        "avatar_url": "https://avatars.githubusercontent.com/u/629193?v=4",
        "gravatar_id": "",
        "url": "https://api.github.com/users/cpeterso",
        "html_url": "https://github.com/cpeterso",
        "followers_url": "https://api.github.com/users/cpeterso/followers",
        "following_url": "https://api.github.com/users/cpeterso/following{/other_user}",
        "gists_url": "https://api.github.com/users/cpeterso/gists{/gist_id}",
        "starred_url": "https://api.github.com/users/cpeterso/starred{/owner}{/repo}",
        "subscriptions_url": "https://api.github.com/users/cpeterso/subscriptions",
        "organizations_url": "https://api.github.com/users/cpeterso/orgs",
        "repos_url": "https://api.github.com/users/cpeterso/repos",
        "events_url": "https://api.github.com/users/cpeterso/events{/privacy}",
        "received_events_url": "https://api.github.com/users/cpeterso/received_events",
        "type": "User",
        "site_admin": false
    },
    "reactions": {
        "url": "https://api.github.com/repos/mozilla-mobile/focus-android/issues/7536/reactions",
        "total_count": 0,
        "+1": 0,
        "-1": 0,
        "laugh": 0,
        "hooray": 0,
        "confused": 0,
        "heart": 0,
        "rocket": 0,
        "eyes": 0
    },
    "timeline_url": "https://api.github.com/repos/mozilla-mobile/focus-android/issues/7536/timeline",
    "performed_via_github_app": null,
    "state_reason": "completed"
}